{"dependencies":[{"name":"vue"},{"name":"./MainApp.vue"}],"generated":{"js":"\"use strict\";\n\nvar _vue = require(\"vue\");\n\nvar _vue2 = _interopRequireDefault(_vue);\n\nvar _MainApp = require(\"./MainApp.vue\");\n\nvar _MainApp2 = _interopRequireDefault(_MainApp);\n\nfunction _interopRequireDefault(obj) { return obj && obj.__esModule ? obj : { default: obj }; }\n\nvar app = new _vue2.default({\n  data: {},\n  render: function render(h) {\n    return h(_MainApp2.default);\n  }\n});\napp.$mount(\"#app\");"},"hash":"487c2ddbdeec1c9e7d28b0e13d2c41cd"}